[{"id":"demake-gaXapTXJ","date":"2018-09-20T04:05:07.077Z","mediaFilename":"demake-gaXapTXJ.png","caption":"extensibility","postedToGit":true,"htmlFragment":"<li class=\"pane\">\n  <div class=\"time-stamp entry-meta\">\n    <a href=\"demake-gaXapTXJ.html\">\n      <time datetime=\"2018-09-20T04:05:07.077Z\">2018-9-20 00:05:07</time>\n    </a>\n  </div><img src=\"media/demake-gaXapTXJ.png\" alt=\"extensibility\"></video><div class=\"media-caption entry-meta\">\n      <a href=\"demake-gaXapTXJ.html\">extensibility</a></div></li>","postedSingleVideoPage":true},{"id":"demake-aGwnfcZF","date":"2018-09-20T08:05:05.817Z","mediaFilename":"demake-aGwnfcZF.png","caption":"Laney","postedToGit":true,"htmlFragment":"<li class=\"pane\">\n  <div class=\"time-stamp entry-meta\">\n    <a href=\"demake-aGwnfcZF.html\">\n      <time datetime=\"2018-09-20T08:05:05.817Z\">2018-9-20 04:05:05</time>\n    </a>\n  </div><img src=\"media/demake-aGwnfcZF.png\" alt=\"Laney\"></video><div class=\"media-caption entry-meta\">\n      <a href=\"demake-aGwnfcZF.html\">Laney</a></div></li>","postedSingleVideoPage":true}]