[{"id":"demake-BsljdDXh","date":"2018-10-27T04:05:02.833Z","mediaFilename":"demake-BsljdDXh.png","caption":"A High Energy Fleet","postedToGit":true,"htmlFragment":"<li class=\"pane\">\n  <div class=\"time-stamp entry-meta\">\n    <a href=\"demake-BsljdDXh.html\">\n      <time datetime=\"2018-10-27T04:05:02.833Z\">2018-10-27 00:05:02</time>\n    </a>\n  </div><img src=\"media/demake-BsljdDXh.png\" alt=\"A High Energy Fleet\"></video><div class=\"media-caption entry-meta\">\n      <a href=\"demake-BsljdDXh.html\">A High Energy Fleet</a></div></li>","postedSingleVideoPage":true},{"id":"demake-ncvhiOAe","date":"2018-10-27T08:05:05.538Z","mediaFilename":"demake-ncvhiOAe.png","caption":"Canfield","postedToGit":true,"htmlFragment":"<li class=\"pane\">\n  <div class=\"time-stamp entry-meta\">\n    <a href=\"demake-ncvhiOAe.html\">\n      <time datetime=\"2018-10-27T08:05:05.538Z\">2018-10-27 04:05:05</time>\n    </a>\n  </div><img src=\"media/demake-ncvhiOAe.png\" alt=\"Canfield\"></video><div class=\"media-caption entry-meta\">\n      <a href=\"demake-ncvhiOAe.html\">Canfield</a></div></li>","postedSingleVideoPage":true},{"id":"demake-rMuGeuxs","date":"2018-10-27T12:05:05.889Z","mediaFilename":"demake-rMuGeuxs.png","caption":"bergamot","postedToGit":true,"htmlFragment":"<li class=\"pane\">\n  <div class=\"time-stamp entry-meta\">\n    <a href=\"demake-rMuGeuxs.html\">\n      <time datetime=\"2018-10-27T12:05:05.889Z\">2018-10-27 08:05:05</time>\n    </a>\n  </div><img src=\"media/demake-rMuGeuxs.png\" alt=\"bergamot\"></video><div class=\"media-caption entry-meta\">\n      <a href=\"demake-rMuGeuxs.html\">bergamot</a></div></li>","postedSingleVideoPage":true},{"id":"demake-LENgzSzR","date":"2018-10-27T16:05:05.081Z","mediaFilename":"demake-LENgzSzR.png","caption":"Keokuk","postedToGit":true,"htmlFragment":"<li class=\"pane\">\n  <div class=\"time-stamp entry-meta\">\n    <a href=\"demake-LENgzSzR.html\">\n      <time datetime=\"2018-10-27T16:05:05.081Z\">2018-10-27 12:05:05</time>\n    </a>\n  </div><img src=\"media/demake-LENgzSzR.png\" alt=\"Keokuk\"></video><div class=\"media-caption entry-meta\">\n      <a href=\"demake-LENgzSzR.html\">Keokuk</a></div></li>","postedSingleVideoPage":true},{"id":"demake-nZOGRjsQ","date":"2018-10-27T20:05:05.422Z","mediaFilename":"demake-nZOGRjsQ.png","caption":"Britney Spears","postedToGit":true,"htmlFragment":"<li class=\"pane\">\n  <div class=\"time-stamp entry-meta\">\n    <a href=\"demake-nZOGRjsQ.html\">\n      <time datetime=\"2018-10-27T20:05:05.422Z\">2018-10-27 16:05:05</time>\n    </a>\n  </div><img src=\"media/demake-nZOGRjsQ.png\" alt=\"Britney Spears\"></video><div class=\"media-caption entry-meta\">\n      <a href=\"demake-nZOGRjsQ.html\">Britney Spears</a></div></li>","postedSingleVideoPage":true},{"id":"demake-XVPBVIUQ","date":"2018-10-28T00:05:04.011Z","mediaFilename":"demake-XVPBVIUQ.png","caption":"Man Enters Space","postedToGit":true,"htmlFragment":"<li class=\"pane\">\n  <div class=\"time-stamp entry-meta\">\n    <a href=\"demake-XVPBVIUQ.html\">\n      <time datetime=\"2018-10-28T00:05:04.011Z\">2018-10-27 20:05:04</time>\n    </a>\n  </div><img src=\"media/demake-XVPBVIUQ.png\" alt=\"Man Enters Space\"></video><div class=\"media-caption entry-meta\">\n      <a href=\"demake-XVPBVIUQ.html\">Man Enters Space</a></div></li>","postedSingleVideoPage":true},{"id":"demake-fQtTCbYd","date":"2018-10-28T04:05:09.070Z","mediaFilename":"demake-fQtTCbYd.png","caption":"Calabrese","postedToGit":true,"htmlFragment":"<li class=\"pane\">\n  <div class=\"time-stamp entry-meta\">\n    <a href=\"demake-fQtTCbYd.html\">\n      <time datetime=\"2018-10-28T04:05:09.070Z\">2018-10-28 00:05:09</time>\n    </a>\n  </div><img src=\"media/demake-fQtTCbYd.png\" alt=\"Calabrese\"></video><div class=\"media-caption entry-meta\">\n      <a href=\"demake-fQtTCbYd.html\">Calabrese</a></div></li>","postedSingleVideoPage":true},{"id":"demake-jWJhjrMa","date":"2018-10-28T08:05:05.583Z","mediaFilename":"demake-jWJhjrMa.png","caption":"The Elephant's Trunk in IC 1396","postedToGit":true,"htmlFragment":"<li class=\"pane\">\n  <div class=\"time-stamp entry-meta\">\n    <a href=\"demake-jWJhjrMa.html\">\n      <time datetime=\"2018-10-28T08:05:05.583Z\">2018-10-28 04:05:05</time>\n    </a>\n  </div><img src=\"media/demake-jWJhjrMa.png\" alt=\"The Elephant's Trunk in IC 1396\"></video><div class=\"media-caption entry-meta\">\n      <a href=\"demake-jWJhjrMa.html\">The Elephant's Trunk in IC 1396</a></div></li>","postedSingleVideoPage":true},{"id":"demake-MkVaGKid","date":"2018-10-28T12:05:06.759Z","mediaFilename":"demake-MkVaGKid.png","caption":"abusing","postedToGit":true,"htmlFragment":"<li class=\"pane\">\n  <div class=\"time-stamp entry-meta\">\n    <a href=\"demake-MkVaGKid.html\">\n      <time datetime=\"2018-10-28T12:05:06.759Z\">2018-10-28 08:05:06</time>\n    </a>\n  </div><img src=\"media/demake-MkVaGKid.png\" alt=\"abusing\"></video><div class=\"media-caption entry-meta\">\n      <a href=\"demake-MkVaGKid.html\">abusing</a></div></li>","postedSingleVideoPage":true},{"id":"demake-nJExIVME","date":"2018-10-28T16:05:06.781Z","mediaFilename":"demake-nJExIVME.png","caption":"acyclovir","postedToGit":true,"htmlFragment":"<li class=\"pane\">\n  <div class=\"time-stamp entry-meta\">\n    <a href=\"demake-nJExIVME.html\">\n      <time datetime=\"2018-10-28T16:05:06.781Z\">2018-10-28 12:05:06</time>\n    </a>\n  </div><img src=\"media/demake-nJExIVME.png\" alt=\"acyclovir\"></video><div class=\"media-caption entry-meta\">\n      <a href=\"demake-nJExIVME.html\">acyclovir</a></div></li>","postedSingleVideoPage":true},{"id":"demake-tVJRsENj","date":"2018-10-28T20:05:05.749Z","mediaFilename":"demake-tVJRsENj.png","caption":"Evangelist","postedToGit":true,"htmlFragment":"<li class=\"pane\">\n  <div class=\"time-stamp entry-meta\">\n    <a href=\"demake-tVJRsENj.html\">\n      <time datetime=\"2018-10-28T20:05:05.749Z\">2018-10-28 16:05:05</time>\n    </a>\n  </div><img src=\"media/demake-tVJRsENj.png\" alt=\"Evangelist\"></video><div class=\"media-caption entry-meta\">\n      <a href=\"demake-tVJRsENj.html\">Evangelist</a></div></li>","postedSingleVideoPage":true},{"id":"demake-wKPfPWdh","date":"2018-10-29T00:05:05.906Z","mediaFilename":"demake-wKPfPWdh.png","caption":"flipper","postedToGit":true,"htmlFragment":"<li class=\"pane\">\n  <div class=\"time-stamp entry-meta\">\n    <a href=\"demake-wKPfPWdh.html\">\n      <time datetime=\"2018-10-29T00:05:05.906Z\">2018-10-28 20:05:05</time>\n    </a>\n  </div><img src=\"media/demake-wKPfPWdh.png\" alt=\"flipper\"></video><div class=\"media-caption entry-meta\">\n      <a href=\"demake-wKPfPWdh.html\">flipper</a></div></li>","postedSingleVideoPage":true},{"id":"demake-UrIZnbMQ","date":"2018-10-29T04:05:07.190Z","mediaFilename":"demake-UrIZnbMQ.png","caption":"anchoress","postedToGit":true,"htmlFragment":"<li class=\"pane\">\n  <div class=\"time-stamp entry-meta\">\n    <a href=\"demake-UrIZnbMQ.html\">\n      <time datetime=\"2018-10-29T04:05:07.190Z\">2018-10-29 00:05:07</time>\n    </a>\n  </div><img src=\"media/demake-UrIZnbMQ.png\" alt=\"anchoress\"></video><div class=\"media-caption entry-meta\">\n      <a href=\"demake-UrIZnbMQ.html\">anchoress</a></div></li>","postedSingleVideoPage":true},{"id":"demake-XBxJwFmp","date":"2018-10-29T08:05:05.649Z","mediaFilename":"demake-XBxJwFmp.png","caption":"Magpie","postedToGit":true,"htmlFragment":"<li class=\"pane\">\n  <div class=\"time-stamp entry-meta\">\n    <a href=\"demake-XBxJwFmp.html\">\n      <time datetime=\"2018-10-29T08:05:05.649Z\">2018-10-29 04:05:05</time>\n    </a>\n  </div><img src=\"media/demake-XBxJwFmp.png\" alt=\"Magpie\"></video><div class=\"media-caption entry-meta\">\n      <a href=\"demake-XBxJwFmp.html\">Magpie</a></div></li>","postedSingleVideoPage":true},{"id":"demake-BEFWaGGq","date":"2018-10-29T12:05:05.451Z","mediaFilename":"demake-BEFWaGGq.png","caption":"Kant's","postedToGit":true,"htmlFragment":"<li class=\"pane\">\n  <div class=\"time-stamp entry-meta\">\n    <a href=\"demake-BEFWaGGq.html\">\n      <time datetime=\"2018-10-29T12:05:05.451Z\">2018-10-29 08:05:05</time>\n    </a>\n  </div><img src=\"media/demake-BEFWaGGq.png\" alt=\"Kant's\"></video><div class=\"media-caption entry-meta\">\n      <a href=\"demake-BEFWaGGq.html\">Kant's</a></div></li>","postedSingleVideoPage":true},{"id":"demake-oDTrHZkH","date":"2018-10-29T16:05:07.802Z","mediaFilename":"demake-oDTrHZkH.png","caption":"Singaporeans","postedToGit":true,"htmlFragment":"<li class=\"pane\">\n  <div class=\"time-stamp entry-meta\">\n    <a href=\"demake-oDTrHZkH.html\">\n      <time datetime=\"2018-10-29T16:05:07.802Z\">2018-10-29 12:05:07</time>\n    </a>\n  </div><img src=\"media/demake-oDTrHZkH.png\" alt=\"Singaporeans\"></video><div class=\"media-caption entry-meta\">\n      <a href=\"demake-oDTrHZkH.html\">Singaporeans</a></div></li>","postedSingleVideoPage":true}]