[{"id":"demake-swIUcJGX","date":"2018-10-30T12:05:09.208Z","mediaFilename":"demake-swIUcJGX.png","caption":"acquirements","postedToGit":true,"htmlFragment":"<li class=\"pane\">\n  <div class=\"time-stamp entry-meta\">\n    <a href=\"demake-swIUcJGX.html\">\n      <time datetime=\"2018-10-30T12:05:09.208Z\">2018-10-30 08:05:09</time>\n    </a>\n  </div><img src=\"media/demake-swIUcJGX.png\" alt=\"acquirements\"></video><div class=\"media-caption entry-meta\">\n      <a href=\"demake-swIUcJGX.html\">acquirements</a></div></li>","postedSingleVideoPage":true},{"id":"demake-JThvhael","date":"2018-10-30T16:05:05.081Z","mediaFilename":"demake-JThvhael.png","caption":"Sargent","postedToGit":true,"htmlFragment":"<li class=\"pane\">\n  <div class=\"time-stamp entry-meta\">\n    <a href=\"demake-JThvhael.html\">\n      <time datetime=\"2018-10-30T16:05:05.081Z\">2018-10-30 12:05:05</time>\n    </a>\n  </div><img src=\"media/demake-JThvhael.png\" alt=\"Sargent\"></video><div class=\"media-caption entry-meta\">\n      <a href=\"demake-JThvhael.html\">Sargent</a></div></li>","postedSingleVideoPage":true},{"id":"demake-JWQSgqjV","date":"2018-10-30T20:05:10.660Z","mediaFilename":"demake-JWQSgqjV.png","caption":"Gamay","postedToGit":true,"htmlFragment":"<li class=\"pane\">\n  <div class=\"time-stamp entry-meta\">\n    <a href=\"demake-JWQSgqjV.html\">\n      <time datetime=\"2018-10-30T20:05:10.660Z\">2018-10-30 16:05:10</time>\n    </a>\n  </div><img src=\"media/demake-JWQSgqjV.png\" alt=\"Gamay\"></video><div class=\"media-caption entry-meta\">\n      <a href=\"demake-JWQSgqjV.html\">Gamay</a></div></li>","postedSingleVideoPage":true},{"id":"demake-ChPJCheC","date":"2018-10-31T00:05:07.241Z","mediaFilename":"demake-ChPJCheC.png","caption":"Panzer","postedToGit":true,"htmlFragment":"<li class=\"pane\">\n  <div class=\"time-stamp entry-meta\">\n    <a href=\"demake-ChPJCheC.html\">\n      <time datetime=\"2018-10-31T00:05:07.241Z\">2018-10-30 20:05:07</time>\n    </a>\n  </div><img src=\"media/demake-ChPJCheC.png\" alt=\"Panzer\"></video><div class=\"media-caption entry-meta\">\n      <a href=\"demake-ChPJCheC.html\">Panzer</a></div></li>","postedSingleVideoPage":true},{"id":"demake-rNLgjxsK","date":"2018-10-31T04:05:05.580Z","mediaFilename":"demake-rNLgjxsK.png","caption":"burrito","postedToGit":true,"htmlFragment":"<li class=\"pane\">\n  <div class=\"time-stamp entry-meta\">\n    <a href=\"demake-rNLgjxsK.html\">\n      <time datetime=\"2018-10-31T04:05:05.580Z\">2018-10-31 00:05:05</time>\n    </a>\n  </div><img src=\"media/demake-rNLgjxsK.png\" alt=\"burrito\"></video><div class=\"media-caption entry-meta\">\n      <a href=\"demake-rNLgjxsK.html\">burrito</a></div></li>","postedSingleVideoPage":true},{"id":"demake-AUnRRYgB","date":"2018-10-31T08:05:06.070Z","mediaFilename":"demake-AUnRRYgB.png","caption":"evocation","postedToGit":true,"htmlFragment":"<li class=\"pane\">\n  <div class=\"time-stamp entry-meta\">\n    <a href=\"demake-AUnRRYgB.html\">\n      <time datetime=\"2018-10-31T08:05:06.070Z\">2018-10-31 04:05:06</time>\n    </a>\n  </div><img src=\"media/demake-AUnRRYgB.png\" alt=\"evocation\"></video><div class=\"media-caption entry-meta\">\n      <a href=\"demake-AUnRRYgB.html\">evocation</a></div></li>","postedSingleVideoPage":true},{"id":"demake-kGbMeEog","date":"2018-10-31T12:05:04.214Z","mediaFilename":"demake-kGbMeEog.png","caption":"A Rare Hybrid Solar Eclipse","postedToGit":true,"htmlFragment":"<li class=\"pane\">\n  <div class=\"time-stamp entry-meta\">\n    <a href=\"demake-kGbMeEog.html\">\n      <time datetime=\"2018-10-31T12:05:04.214Z\">2018-10-31 08:05:04</time>\n    </a>\n  </div><img src=\"media/demake-kGbMeEog.png\" alt=\"A Rare Hybrid Solar Eclipse\"></video><div class=\"media-caption entry-meta\">\n      <a href=\"demake-kGbMeEog.html\">A Rare Hybrid Solar Eclipse</a></div></li>","postedSingleVideoPage":true},{"id":"demake-jLkPjPjN","date":"2018-10-31T16:05:06.189Z","mediaFilename":"demake-jLkPjPjN.png","caption":"overdoses","postedToGit":true,"htmlFragment":"<li class=\"pane\">\n  <div class=\"time-stamp entry-meta\">\n    <a href=\"demake-jLkPjPjN.html\">\n      <time datetime=\"2018-10-31T16:05:06.189Z\">2018-10-31 12:05:06</time>\n    </a>\n  </div><img src=\"media/demake-jLkPjPjN.png\" alt=\"overdoses\"></video><div class=\"media-caption entry-meta\">\n      <a href=\"demake-jLkPjPjN.html\">overdoses</a></div></li>","postedSingleVideoPage":true},{"id":"demake-sXUKRicG","date":"2018-10-31T20:05:07.211Z","mediaFilename":"demake-sXUKRicG.png","caption":"Melba","postedToGit":true,"htmlFragment":"<li class=\"pane\">\n  <div class=\"time-stamp entry-meta\">\n    <a href=\"demake-sXUKRicG.html\">\n      <time datetime=\"2018-10-31T20:05:07.211Z\">2018-10-31 16:05:07</time>\n    </a>\n  </div><img src=\"media/demake-sXUKRicG.png\" alt=\"Melba\"></video><div class=\"media-caption entry-meta\">\n      <a href=\"demake-sXUKRicG.html\">Melba</a></div></li>","postedSingleVideoPage":true},{"id":"demake-OLZXODKd","date":"2018-11-01T00:05:03.795Z","mediaFilename":"demake-OLZXODKd.png","caption":"A Step Toward Gravitational Wave Detection","postedToGit":true,"htmlFragment":"<li class=\"pane\">\n  <div class=\"time-stamp entry-meta\">\n    <a href=\"demake-OLZXODKd.html\">\n      <time datetime=\"2018-11-01T00:05:03.795Z\">2018-10-31 20:05:03</time>\n    </a>\n  </div><img src=\"media/demake-OLZXODKd.png\" alt=\"A Step Toward Gravitational Wave Detection\"></video><div class=\"media-caption entry-meta\">\n      <a href=\"demake-OLZXODKd.html\">A Step Toward Gravitational Wave Detection</a></div></li>","postedSingleVideoPage":true},{"id":"demake-xdJzEUqa","date":"2018-11-01T04:05:07.915Z","mediaFilename":"demake-xdJzEUqa.png","caption":"cauld","postedToGit":true,"htmlFragment":"<li class=\"pane\">\n  <div class=\"time-stamp entry-meta\">\n    <a href=\"demake-xdJzEUqa.html\">\n      <time datetime=\"2018-11-01T04:05:07.915Z\">2018-11-1 00:05:07</time>\n    </a>\n  </div><img src=\"media/demake-xdJzEUqa.png\" alt=\"cauld\"></video><div class=\"media-caption entry-meta\">\n      <a href=\"demake-xdJzEUqa.html\">cauld</a></div></li>","postedSingleVideoPage":true},{"id":"demake-tCeGCBsm","date":"2018-11-01T08:05:06.516Z","mediaFilename":"demake-tCeGCBsm.png","caption":"atrium","postedToGit":true,"htmlFragment":"<li class=\"pane\">\n  <div class=\"time-stamp entry-meta\">\n    <a href=\"demake-tCeGCBsm.html\">\n      <time datetime=\"2018-11-01T08:05:06.516Z\">2018-11-1 04:05:06</time>\n    </a>\n  </div><img src=\"media/demake-tCeGCBsm.png\" alt=\"atrium\"></video><div class=\"media-caption entry-meta\">\n      <a href=\"demake-tCeGCBsm.html\">atrium</a></div></li>","postedSingleVideoPage":true}]