[{"id":"demake-NZTiKdLx","date":"2018-11-16T09:05:07.151Z","mediaFilename":"demake-NZTiKdLx.png","caption":"developers","postedToGit":true,"htmlFragment":"<li class=\"pane\">\n  <div class=\"time-stamp entry-meta\">\n    <a href=\"demake-NZTiKdLx.html\">\n      <time datetime=\"2018-11-16T09:05:07.151Z\">2018-11-16 04:05:07</time>\n    </a>\n  </div><img src=\"media/demake-NZTiKdLx.png\" alt=\"developers\"></video><div class=\"media-caption entry-meta\">\n      <a href=\"demake-NZTiKdLx.html\">developers</a></div></li>","postedSingleVideoPage":true},{"id":"demake-XykKiZZo","date":"2018-11-16T13:05:06.859Z","mediaFilename":"demake-XykKiZZo.png","caption":"aerosols","postedToGit":true,"htmlFragment":"<li class=\"pane\">\n  <div class=\"time-stamp entry-meta\">\n    <a href=\"demake-XykKiZZo.html\">\n      <time datetime=\"2018-11-16T13:05:06.859Z\">2018-11-16 08:05:06</time>\n    </a>\n  </div><img src=\"media/demake-XykKiZZo.png\" alt=\"aerosols\"></video><div class=\"media-caption entry-meta\">\n      <a href=\"demake-XykKiZZo.html\">aerosols</a></div></li>","postedSingleVideoPage":true},{"id":"demake-eUnTSfde","date":"2018-11-16T17:05:04.391Z","mediaFilename":"demake-eUnTSfde.png","caption":"Wisps of the Iris Nebula","postedToGit":true,"htmlFragment":"<li class=\"pane\">\n  <div class=\"time-stamp entry-meta\">\n    <a href=\"demake-eUnTSfde.html\">\n      <time datetime=\"2018-11-16T17:05:04.391Z\">2018-11-16 12:05:04</time>\n    </a>\n  </div><img src=\"media/demake-eUnTSfde.png\" alt=\"Wisps of the Iris Nebula\"></video><div class=\"media-caption entry-meta\">\n      <a href=\"demake-eUnTSfde.html\">Wisps of the Iris Nebula</a></div></li>","postedSingleVideoPage":true}]